{"level":"info","hostName":"ip-172-31-35-57.ap-southeast-2.compute.internal","time":"2022-06-16T08:36:34Z","message":"hostName determined"}
{"level":"info","version":"v0.9.5","time":"2022-06-16T08:36:34Z","message":"version determined"}
{"level":"info","srvID":"df490b4d","time":"2022-06-16T08:36:34Z","message":"srvID determined"}
{"level":"info","srvId":"df490b4d","timeZone":"UTC","time":"2022-06-16T08:36:34Z","message":"timeZone determined"}
{"level":"info","srvId":"df490b4d","time":"2022-06-16T08:36:34Z","message":"setting global log level to INFO"}
{"level":"info","srvId":"df490b4d","time":"2022-06-16T08:36:34Z","message":"attempting config from file 'config.yml'"}
{"level":"info","srvId":"df490b4d","time":"2022-06-16T08:36:34Z","message":"parsed config with 1 live routes"}
{"level":"info","srvId":"df490b4d","time":"2022-06-16T08:36:34Z","message":"found cache dir in user home"}
{"level":"info","srvId":"df490b4d","upMaxIdleConns":32768,"upMaxIdleConnsPerHost":32768,"upTransportDialTimeoutSecs":10,"upTlsHandshakeTimeoutSecs":10,"upIdleConnTimeoutSecs":10,"upReadTimeoutSecs":30,"upTransportDialKeepAliveIntervalSecs":1.111111111,"upTlsInsecureSkipVerify":true,"time":"2022-06-16T08:36:34Z","message":"server derived upstream params"}
{"level":"info","srvId":"df490b4d","dwnMaxBodyBytes":65535,"dwnReadTimeoutSeconds":30,"dwnRoundTripTimeoutSeconds":60,"dwnIdleConnTimeoutSeconds":10,"time":"2022-06-16T08:36:34Z","message":"server derived downstream params"}
{"level":"info","srvId":"df490b4d","time":"2022-06-16T08:36:34Z","message":"j8a v0.9.5 listener(s) init on HTTP:8080..."}
{"level":"info","srvId":"df490b4d","pid":9182,"pidCpuCorePct":"0.00","pidMemPct":"0.02","pidDwnOpenTcpConns":0,"pidDwnMaxOpenTcpConns":0,"pidUpOpenTcpConns":0,"pidUpMaxOpenTcpConns":0,"pidMemRssBytes":9523200,"pidMemVmsBytes":730943488,"pidMemSwapBytes":0,"pidOSThreads":6,"pidOSUlimit":1048576,"time":"2022-06-16T08:36:40Z","message":"server performance"}
{"level":"info","srvId":"df490b4d","pid":9182,"pidCpuCorePct":"0.00","pidMemPct":"0.02","pidDwnOpenTcpConns":0,"pidDwnMaxOpenTcpConns":0,"pidUpOpenTcpConns":0,"pidUpMaxOpenTcpConns":0,"pidMemRssBytes":9523200,"pidMemVmsBytes":730943488,"pidMemSwapBytes":0,"pidOSThreads":6,"pidOSUlimit":1048576,"time":"2022-06-16T08:37:42Z","message":"server performance"}
{"level":"info","srvId":"df490b4d","pid":9182,"pidCpuCorePct":"1567.35","pidMemPct":"4.91","pidDwnOpenTcpConns":3413,"pidDwnMaxOpenTcpConns":3413,"pidUpOpenTcpConns":2012,"pidUpMaxOpenTcpConns":2012,"pidMemRssBytes":2115424256,"pidMemVmsBytes":2785136640,"pidMemSwapBytes":0,"pidOSThreads":19,"pidOSUlimit":1048576,"time":"2022-06-16T08:38:44Z","message":"server performance"}
{"level":"info","srvId":"df490b4d","pid":9182,"pidCpuCorePct":"1580.79","pidMemPct":"5.53","pidDwnOpenTcpConns":4096,"pidDwnMaxOpenTcpConns":4096,"pidUpOpenTcpConns":2433,"pidUpMaxOpenTcpConns":2433,"pidMemRssBytes":2384793600,"pidMemVmsBytes":3068911616,"pidMemSwapBytes":0,"pidOSThreads":19,"pidOSUlimit":1048576,"time":"2022-06-16T08:39:47Z","message":"server performance"}
{"level":"info","srvId":"df490b4d","pid":9182,"pidCpuCorePct":"1579.15","pidMemPct":"5.18","pidDwnOpenTcpConns":4096,"pidDwnMaxOpenTcpConns":4096,"pidUpOpenTcpConns":2355,"pidUpMaxOpenTcpConns":2433,"pidMemRssBytes":2233016320,"pidMemVmsBytes":3069173760,"pidMemSwapBytes":0,"pidOSThreads":19,"pidOSUlimit":1048576,"time":"2022-06-16T08:40:49Z","message":"server performance"}
{"level":"info","srvId":"df490b4d","pid":9182,"pidCpuCorePct":"1586.88","pidMemPct":"5.06","pidDwnOpenTcpConns":4096,"pidDwnMaxOpenTcpConns":4096,"pidUpOpenTcpConns":2338,"pidUpMaxOpenTcpConns":2433,"pidMemRssBytes":2182184960,"pidMemVmsBytes":3069173760,"pidMemSwapBytes":0,"pidOSThreads":19,"pidOSUlimit":1048576,"time":"2022-06-16T08:41:51Z","message":"server performance"}
{"level":"info","srvId":"df490b4d","pid":9182,"pidCpuCorePct":"1572.78","pidMemPct":"6.18","pidDwnOpenTcpConns":170,"pidDwnMaxOpenTcpConns":4096,"pidUpOpenTcpConns":474,"pidUpMaxOpenTcpConns":2433,"pidMemRssBytes":2666852352,"pidMemVmsBytes":3419353088,"pidMemSwapBytes":0,"pidOSThreads":19,"pidOSUlimit":1048576,"time":"2022-06-16T08:42:53Z","message":"server performance"}
